odoo10_addon_l10n_nl_partner_name-10.0.1.1.1-nspkg.pth
odoo/addons/l10n_nl_partner_name/README.rst
odoo/addons/l10n_nl_partner_name/__init__.py
odoo/addons/l10n_nl_partner_name/__manifest__.py
odoo/addons/l10n_nl_partner_name/data/ir.config_parameter.xml
odoo/addons/l10n_nl_partner_name/i18n/l10n_nl_partner_name.pot
odoo/addons/l10n_nl_partner_name/i18n/nl.po
odoo/addons/l10n_nl_partner_name/model/__init__.py
odoo/addons/l10n_nl_partner_name/model/res_partner.py
odoo/addons/l10n_nl_partner_name/scripts/guess_names.py
odoo/addons/l10n_nl_partner_name/static/description/icon.png
odoo/addons/l10n_nl_partner_name/static/src/img/icon.png
odoo/addons/l10n_nl_partner_name/tests/__init__.py
odoo/addons/l10n_nl_partner_name/tests/test_l10n_nl_partner_name.py
odoo/addons/l10n_nl_partner_name/view/res_partner.xml
odoo10_addon_l10n_nl_partner_name-10.0.1.1.1.dist-info/METADATA
odoo10_addon_l10n_nl_partner_name-10.0.1.1.1.dist-info/WHEEL
odoo10_addon_l10n_nl_partner_name-10.0.1.1.1.dist-info/namespace_packages.txt
odoo10_addon_l10n_nl_partner_name-10.0.1.1.1.dist-info/top_level.txt
odoo10_addon_l10n_nl_partner_name-10.0.1.1.1.dist-info/RECORD
