Metadata-Version: 2.1
Name: odoo10-addon-l10n-nl-partner-name
Version: 10.0.1.1.1
Summary: Dutch partner names
Home-page: UNKNOWN
Author: Therp BV, Odoo Community Association (OCA)
Author-email: support@odoo-community.org
License: AGPL-3
Platform: UNKNOWN
Classifier: Programming Language :: Python
Classifier: Framework :: Odoo
Classifier: License :: OSI Approved :: GNU Affero General Public License v3
Requires-Python: ~=2.7
Requires-Dist: mako
Requires-Dist: odoo10-addon-base-view-inheritance-extension
Requires-Dist: odoo10-addon-partner-firstname
Requires-Dist: odoo (<10.1dev,>=10.0)
